{
	"cellModels":[
		{
			"dimension":4,
			"Row":1,
			"Col":1,
			"Value":13,
			"Candidates":2066,
			"Initial":true,
			"Sol":13
		},
		{
			"dimension":4,
			"Row":2,
			"Col":1,
			"Value":3,
			"Candidates":35090,
			"Initial":true,
			"Sol":3
		},
		{
			"dimension":4,
			"Row":3,
			"Col":1,
			"Value":15,
			"Candidates":272,
			"Initial":true,
			"Sol":15
		},
		{
			"dimension":4,
			"Row":4,
			"Col":1,
			"Value":0,
			"Candidates":33042,
			"Initial":false,
			"Sol":16
		},
		{
			"dimension":4,
			"Row":5,
			"Col":1,
			"Value":0,
			"Candidates":2048,
			"Initial":false,
			"Sol":12
		},
		{
			"dimension":4,
			"Row":6,
			"Col":1,
			"Value":7,
			"Candidates":2560,
			"Initial":true,
			"Sol":7
		},
		{
			"dimension":4,
			"Row":7,
			"Col":1,
			"Value":11,
			"Candidates":2049,
			"Initial":true,
			"Sol":11
		},
		{
			"dimension":4,
			"Row":8,
			"Col":1,
			"Value":8,
			"Candidates":513,
			"Initial":true,
			"Sol":8
		},
		{
			"dimension":4,
			"Row":9,
			"Col":1,
			"Value":0,
			"Candidates":2563,
			"Initial":false,
			"Sol":10
		},
		{
			"dimension":4,
			"Row":10,
			"Col":1,
			"Value":4,
			"Candidates":513,
			"Initial":true,
			"Sol":4
		},
		{
			"dimension":4,
			"Row":11,
			"Col":1,
			"Value":6,
			"Candidates":2577,
			"Initial":true,
			"Sol":6
		},
		{
			"dimension":4,
			"Row":12,
			"Col":1,
			"Value":0,
			"Candidates":274,
			"Initial":false,
			"Sol":2
		},
		{
			"dimension":4,
			"Row":13,
			"Col":1,
			"Value":0,
			"Candidates":35073,
			"Initial":false,
			"Sol":9
		},
		{
			"dimension":4,
			"Row":14,
			"Col":1,
			"Value":14,
			"Candidates":2321,
			"Initial":true,
			"Sol":14
		},
		{
			"dimension":4,
			"Row":15,
			"Col":1,
			"Value":0,
			"Candidates":273,
			"Initial":false,
			"Sol":1
		},
		{
			"dimension":4,
			"Row":16,
			"Col":1,
			"Value":0,
			"Candidates":2321,
			"Initial":false,
			"Sol":5
		},
		{
			"dimension":4,
			"Row":1,
			"Col":2,
			"Value":0,
			"Candidates":2104,
			"Initial":false,
			"Sol":6
		},
		{
			"dimension":4,
			"Row":2,
			"Col":2,
			"Value":14,
			"Candidates":35120,
			"Initial":true,
			"Sol":14
		},
		{
			"dimension":4,
			"Row":3,
			"Col":2,
			"Value":0,
			"Candidates":408,
			"Initial":false,
			"Sol":8
		},
		{
			"dimension":4,
			"Row":4,
			"Col":2,
			"Value":11,
			"Candidates":33176,
			"Initial":true,
			"Sol":11
		},
		{
			"dimension":4,
			"Row":5,
			"Col":2,
			"Value":3,
			"Candidates":2048,
			"Initial":true,
			"Sol":3
		},
		{
			"dimension":4,
			"Row":6,
			"Col":2,
			"Value":0,
			"Candidates":2560,
			"Initial":false,
			"Sol":10
		},
		{
			"dimension":4,
			"Row":7,
			"Col":2,
			"Value":2,
			"Candidates":2089,
			"Initial":true,
			"Sol":2
		},
		{
			"dimension":4,
			"Row":8,
			"Col":2,
			"Value":0,
			"Candidates":553,
			"Initial":false,
			"Sol":1
		},
		{
			"dimension":4,
			"Row":9,
			"Col":2,
			"Value":15,
			"Candidates":6721,
			"Initial":true,
			"Sol":15
		},
		{
			"dimension":4,
			"Row":10,
			"Col":2,
			"Value":0,
			"Candidates":4673,
			"Initial":false,
			"Sol":7
		},
		{
			"dimension":4,
			"Row":11,
			"Col":2,
			"Value":0,
			"Candidates":2577,
			"Initial":false,
			"Sol":5
		},
		{
			"dimension":4,
			"Row":12,
			"Col":2,
			"Value":0,
			"Candidates":336,
			"Initial":false,
			"Sol":9
		},
		{
			"dimension":4,
			"Row":13,
			"Col":2,
			"Value":0,
			"Candidates":35177,
			"Initial":false,
			"Sol":16
		},
		{
			"dimension":4,
			"Row":14,
			"Col":2,
			"Value":0,
			"Candidates":2321,
			"Initial":false,
			"Sol":12
		},
		{
			"dimension":4,
			"Row":15,
			"Col":2,
			"Value":0,
			"Candidates":4473,
			"Initial":false,
			"Sol":13
		},
		{
			"dimension":4,
			"Row":16,
			"Col":2,
			"Value":0,
			"Candidates":2425,
			"Initial":false,
			"Sol":4
		},
		{
			"dimension":4,
			"Row":1,
			"Col":3,
			"Value":10,
			"Candidates":2104,
			"Initial":true,
			"Sol":10
		},
		{
			"dimension":4,
			"Row":2,
			"Col":3,
			"Value":0,
			"Candidates":2096,
			"Initial":false,
			"Sol":12
		},
		{
			"dimension":4,
			"Row":3,
			"Col":3,
			"Value":0,
			"Candidates":24,
			"Initial":false,
			"Sol":5
		},
		{
			"dimension":4,
			"Row":4,
			"Col":3,
			"Value":7,
			"Candidates":24,
			"Initial":true,
			"Sol":7
		},
		{
			"dimension":4,
			"Row":5,
			"Col":3,
			"Value":9,
			"Candidates":26624,
			"Initial":true,
			"Sol":9
		},
		{
			"dimension":4,
			"Row":6,
			"Col":3,
			"Value":16,
			"Candidates":2048,
			"Initial":true,
			"Sol":16
		},
		{
			"dimension":4,
			"Row":7,
			"Col":3,
			"Value":0,
			"Candidates":26665,
			"Initial":false,
			"Sol":14
		},
		{
			"dimension":4,
			"Row":8,
			"Col":3,
			"Value":0,
			"Candidates":8233,
			"Initial":false,
			"Sol":4
		},
		{
			"dimension":4,
			"Row":9,
			"Col":3,
			"Value":0,
			"Candidates":14341,
			"Initial":false,
			"Sol":13
		},
		{
			"dimension":4,
			"Row":10,
			"Col":3,
			"Value":0,
			"Candidates":12289,
			"Initial":false,
			"Sol":1
		},
		{
			"dimension":4,
			"Row":11,
			"Col":3,
			"Value":11,
			"Candidates":10257,
			"Initial":true,
			"Sol":11
		},
		{
			"dimension":4,
			"Row":12,
			"Col":3,
			"Value":8,
			"Candidates":8212,
			"Initial":true,
			"Sol":8
		},
		{
			"dimension":4,
			"Row":13,
			"Col":3,
			"Value":0,
			"Candidates":2093,
			"Initial":false,
			"Sol":3
		},
		{
			"dimension":4,
			"Row":14,
			"Col":3,
			"Value":2,
			"Candidates":2069,
			"Initial":true,
			"Sol":2
		},
		{
			"dimension":4,
			"Row":15,
			"Col":3,
			"Value":0,
			"Candidates":20541,
			"Initial":false,
			"Sol":15
		},
		{
			"dimension":4,
			"Row":16,
			"Col":3,
			"Value":0,
			"Candidates":18489,
			"Initial":false,
			"Sol":6
		},
		{
			"dimension":4,
			"Row":1,
			"Col":4,
			"Value":1,
			"Candidates":2090,
			"Initial":true,
			"Sol":1
		},
		{
			"dimension":4,
			"Row":2,
			"Col":4,
			"Value":0,
			"Candidates":2338,
			"Initial":false,
			"Sol":2
		},
		{
			"dimension":4,
			"Row":3,
			"Col":4,
			"Value":0,
			"Candidates":264,
			"Initial":false,
			"Sol":9
		},
		{
			"dimension":4,
			"Row":4,
			"Col":4,
			"Value":0,
			"Candidates":266,
			"Initial":false,
			"Sol":4
		},
		{
			"dimension":4,
			"Row":5,
			"Col":4,
			"Value":0,
			"Candidates":26624,
			"Initial":false,
			"Sol":15
		},
		{
			"dimension":4,
			"Row":6,
			"Col":4,
			"Value":5,
			"Candidates":2048,
			"Initial":true,
			"Sol":5
		},
		{
			"dimension":4,
			"Row":7,
			"Col":4,
			"Value":0,
			"Candidates":26664,
			"Initial":false,
			"Sol":6
		},
		{
			"dimension":4,
			"Row":8,
			"Col":4,
			"Value":13,
			"Candidates":8232,
			"Initial":true,
			"Sol":13
		},
		{
			"dimension":4,
			"Row":9,
			"Col":4,
			"Value":0,
			"Candidates":10310,
			"Initial":false,
			"Sol":12
		},
		{
			"dimension":4,
			"Row":10,
			"Col":4,
			"Value":16,
			"Candidates":8256,
			"Initial":true,
			"Sol":16
		},
		{
			"dimension":4,
			"Row":11,
			"Col":4,
			"Value":0,
			"Candidates":10240,
			"Initial":false,
			"Sol":14
		},
		{
			"dimension":4,
			"Row":12,
			"Col":4,
			"Value":0,
			"Candidates":8518,
			"Initial":false,
			"Sol":3
		},
		{
			"dimension":4,
			"Row":13,
			"Col":4,
			"Value":8,
			"Candidates":2412,
			"Initial":true,
			"Sol":8
		},
		{
			"dimension":4,
			"Row":14,
			"Col":4,
			"Value":10,
			"Candidates":3332,
			"Initial":true,
			"Sol":10
		},
		{
			"dimension":4,
			"Row":15,
			"Col":4,
			"Value":0,
			"Candidates":17772,
			"Initial":false,
			"Sol":11
		},
		{
			"dimension":4,
			"Row":16,
			"Col":4,
			"Value":0,
			"Candidates":18792,
			"Initial":false,
			"Sol":7
		},
		{
			"dimension":4,
			"Row":1,
			"Col":5,
			"Value":0,
			"Candidates":3154,
			"Initial":false,
			"Sol":5
		},
		{
			"dimension":4,
			"Row":2,
			"Col":5,
			"Value":4,
			"Candidates":3347,
			"Initial":true,
			"Sol":4
		},
		{
			"dimension":4,
			"Row":3,
			"Col":5,
			"Value":0,
			"Candidates":4437,
			"Initial":false,
			"Sol":13
		},
		{
			"dimension":4,
			"Row":4,
			"Col":5,
			"Value":14,
			"Candidates":274,
			"Initial":true,
			"Sol":14
		},
		{
			"dimension":4,
			"Row":5,
			"Col":5,
			"Value":10,
			"Candidates":2112,
			"Initial":true,
			"Sol":10
		},
		{
			"dimension":4,
			"Row":6,
			"Col":5,
			"Value":0,
			"Candidates":7168,
			"Initial":false,
			"Sol":11
		},
		{
			"dimension":4,
			"Row":7,
			"Col":5,
			"Value":0,
			"Candidates":6224,
			"Initial":false,
			"Sol":7
		},
		{
			"dimension":4,
			"Row":8,
			"Col":5,
			"Value":15,
			"Candidates":1104,
			"Initial":true,
			"Sol":15
		},
		{
			"dimension":4,
			"Row":9,
			"Col":5,
			"Value":0,
			"Candidates":71,
			"Initial":false,
			"Sol":2
		},
		{
			"dimension":4,
			"Row":10,
			"Col":5,
			"Value":8,
			"Candidates":1089,
			"Initial":true,
			"Sol":8
		},
		{
			"dimension":4,
			"Row":11,
			"Col":5,
			"Value":0,
			"Candidates":1,
			"Initial":false,
			"Sol":1
		},
		{
			"dimension":4,
			"Row":12,
			"Col":5,
			"Value":6,
			"Candidates":1094,
			"Initial":true,
			"Sol":6
		},
		{
			"dimension":4,
			"Row":13,
			"Col":5,
			"Value":0,
			"Candidates":2309,
			"Initial":false,
			"Sol":12
		},
		{
			"dimension":4,
			"Row":14,
			"Col":5,
			"Value":0,
			"Candidates":2325,
			"Initial":false,
			"Sol":3
		},
		{
			"dimension":4,
			"Row":15,
			"Col":5,
			"Value":16,
			"Candidates":277,
			"Initial":true,
			"Sol":16
		},
		{
			"dimension":4,
			"Row":16,
			"Col":5,
			"Value":0,
			"Candidates":2321,
			"Initial":false,
			"Sol":9
		},
		{
			"dimension":4,
			"Row":1,
			"Col":6,
			"Value":15,
			"Candidates":1104,
			"Initial":true,
			"Sol":15
		},
		{
			"dimension":4,
			"Row":2,
			"Col":6,
			"Value":8,
			"Candidates":1040,
			"Initial":true,
			"Sol":8
		},
		{
			"dimension":4,
			"Row":3,
			"Col":6,
			"Value":0,
			"Candidates":84,
			"Initial":false,
			"Sol":7
		},
		{
			"dimension":4,
			"Row":4,
			"Col":6,
			"Value":0,
			"Candidates":528,
			"Initial":false,
			"Sol":10
		},
		{
			"dimension":4,
			"Row":5,
			"Col":6,
			"Value":1,
			"Candidates":32832,
			"Initial":true,
			"Sol":1
		},
		{
			"dimension":4,
			"Row":6,
			"Col":6,
			"Value":14,
			"Candidates":1024,
			"Initial":true,
			"Sol":14
		},
		{
			"dimension":4,
			"Row":7,
			"Col":6,
			"Value":0,
			"Candidates":32888,
			"Initial":false,
			"Sol":4
		},
		{
			"dimension":4,
			"Row":8,
			"Col":6,
			"Value":9,
			"Candidates":1144,
			"Initial":true,
			"Sol":9
		},
		{
			"dimension":4,
			"Row":9,
			"Col":6,
			"Value":0,
			"Candidates":32836,
			"Initial":false,
			"Sol":3
		},
		{
			"dimension":4,
			"Row":10,
			"Col":6,
			"Value":0,
			"Candidates":1088,
			"Initial":false,
			"Sol":11
		},
		{
			"dimension":4,
			"Row":11,
			"Col":6,
			"Value":0,
			"Candidates":32768,
			"Initial":false,
			"Sol":16
		},
		{
			"dimension":4,
			"Row":12,
			"Col":6,
			"Value":12,
			"Candidates":33860,
			"Initial":true,
			"Sol":12
		},
		{
			"dimension":4,
			"Row":13,
			"Col":6,
			"Value":13,
			"Candidates":556,
			"Initial":true,
			"Sol":13
		},
		{
			"dimension":4,
			"Row":14,
			"Col":6,
			"Value":0,
			"Candidates":20,
			"Initial":false,
			"Sol":5
		},
		{
			"dimension":4,
			"Row":15,
			"Col":6,
			"Value":0,
			"Candidates":572,
			"Initial":false,
			"Sol":6
		},
		{
			"dimension":4,
			"Row":16,
			"Col":6,
			"Value":2,
			"Candidates":568,
			"Initial":true,
			"Sol":2
		},
		{
			"dimension":4,
			"Row":1,
			"Col":7,
			"Value":16,
			"Candidates":2112,
			"Initial":true,
			"Sol":16
		},
		{
			"dimension":4,
			"Row":2,
			"Col":7,
			"Value":0,
			"Candidates":2305,
			"Initial":false,
			"Sol":1
		},
		{
			"dimension":4,
			"Row":3,
			"Col":7,
			"Value":6,
			"Candidates":4417,
			"Initial":true,
			"Sol":6
		},
		{
			"dimension":4,
			"Row":4,
			"Col":7,
			"Value":0,
			"Candidates":256,
			"Initial":false,
			"Sol":9
		},
		{
			"dimension":4,
			"Row":5,
			"Col":7,
			"Value":2,
			"Candidates":2112,
			"Initial":true,
			"Sol":2
		},
		{
			"dimension":4,
			"Row":6,
			"Col":7,
			"Value":0,
			"Candidates":6272,
			"Initial":false,
			"Sol":13
		},
		{
			"dimension":4,
			"Row":7,
			"Col":7,
			"Value":0,
			"Candidates":6336,
			"Initial":false,
			"Sol":12
		},
		{
			"dimension":4,
			"Row":8,
			"Col":7,
			"Value":3,
			"Candidates":64,
			"Initial":true,
			"Sol":3
		},
		{
			"dimension":4,
			"Row":9,
			"Col":7,
			"Value":0,
			"Candidates":8257,
			"Initial":false,
			"Sol":7
		},
		{
			"dimension":4,
			"Row":10,
			"Col":7,
			"Value":5,
			"Candidates":24641,
			"Initial":true,
			"Sol":5
		},
		{
			"dimension":4,
			"Row":11,
			"Col":7,
			"Value":4,
			"Candidates":24577,
			"Initial":true,
			"Sol":4
		},
		{
			"dimension":4,
			"Row":12,
			"Col":7,
			"Value":10,
			"Candidates":24640,
			"Initial":true,
			"Sol":10
		},
		{
			"dimension":4,
			"Row":13,
			"Col":7,
			"Value":11,
			"Candidates":10497,
			"Initial":true,
			"Sol":11
		},
		{
			"dimension":4,
			"Row":14,
			"Col":7,
			"Value":0,
			"Candidates":2433,
			"Initial":false,
			"Sol":8
		},
		{
			"dimension":4,
			"Row":15,
			"Col":7,
			"Value":0,
			"Candidates":24833,
			"Initial":false,
			"Sol":14
		},
		{
			"dimension":4,
			"Row":16,
			"Col":7,
			"Value":0,
			"Candidates":27009,
			"Initial":false,
			"Sol":15
		},
		{
			"dimension":4,
			"Row":1,
			"Col":8,
			"Value":0,
			"Candidates":3090,
			"Initial":false,
			"Sol":12
		},
		{
			"dimension":4,
			"Row":2,
			"Col":8,
			"Value":0,
			"Candidates":3091,
			"Initial":false,
			"Sol":11
		},
		{
			"dimension":4,
			"Row":3,
			"Col":8,
			"Value":0,
			"Candidates":21,
			"Initial":false,
			"Sol":3
		},
		{
			"dimension":4,
			"Row":4,
			"Col":8,
			"Value":0,
			"Candidates":530,
			"Initial":false,
			"Sol":2
		},
		{
			"dimension":4,
			"Row":5,
			"Col":8,
			"Value":0,
			"Candidates":34816,
			"Initial":false,
			"Sol":16
		},
		{
			"dimension":4,
			"Row":6,
			"Col":8,
			"Value":0,
			"Candidates":3200,
			"Initial":false,
			"Sol":8
		},
		{
			"dimension":4,
			"Row":7,
			"Col":8,
			"Value":0,
			"Candidates":35000,
			"Initial":false,
			"Sol":5
		},
		{
			"dimension":4,
			"Row":8,
			"Col":8,
			"Value":0,
			"Candidates":1080,
			"Initial":false,
			"Sol":6
		},
		{
			"dimension":4,
			"Row":9,
			"Col":8,
			"Value":9,
			"Candidates":40967,
			"Initial":true,
			"Sol":9
		},
		{
			"dimension":4,
			"Row":10,
			"Col":8,
			"Value":0,
			"Candidates":25601,
			"Initial":false,
			"Sol":14
		},
		{
			"dimension":4,
			"Row":11,
			"Col":8,
			"Value":0,
			"Candidates":57345,
			"Initial":false,
			"Sol":15
		},
		{
			"dimension":4,
			"Row":12,
			"Col":8,
			"Value":13,
			"Candidates":58374,
			"Initial":true,
			"Sol":13
		},
		{
			"dimension":4,
			"Row":13,
			"Col":8,
			"Value":0,
			"Candidates":10797,
			"Initial":false,
			"Sol":10
		},
		{
			"dimension":4,
			"Row":14,
			"Col":8,
			"Value":7,
			"Candidates":2197,
			"Initial":true,
			"Sol":7
		},
		{
			"dimension":4,
			"Row":15,
			"Col":8,
			"Value":0,
			"Candidates":25149,
			"Initial":false,
			"Sol":4
		},
		{
			"dimension":4,
			"Row":16,
			"Col":8,
			"Value":0,
			"Candidates":27321,
			"Initial":false,
			"Sol":1
		},
		{
			"dimension":4,
			"Row":1,
			"Col":9,
			"Value":14,
			"Candidates":104,
			"Initial":true,
			"Sol":14
		},
		{
			"dimension":4,
			"Row":2,
			"Col":9,
			"Value":0,
			"Candidates":16417,
			"Initial":false,
			"Sol":6
		},
		{
			"dimension":4,
			"Row":3,
			"Col":9,
			"Value":0,
			"Candidates":201,
			"Initial":false,
			"Sol":4
		},
		{
			"dimension":4,
			"Row":4,
			"Col":9,
			"Value":0,
			"Candidates":16520,
			"Initial":false,
			"Sol":8
		},
		{
			"dimension":4,
			"Row":5,
			"Col":9,
			"Value":13,
			"Candidates":32832,
			"Initial":true,
			"Sol":13
		},
		{
			"dimension":4,
			"Row":6,
			"Col":9,
			"Value":0,
			"Candidates":256,
			"Initial":false,
			"Sol":9
		},
		{
			"dimension":4,
			"Row":7,
			"Col":9,
			"Value":0,
			"Candidates":33089,
			"Initial":false,
			"Sol":16
		},
		{
			"dimension":4,
			"Row":8,
			"Col":9,
			"Value":12,
			"Candidates":65,
			"Initial":true,
			"Sol":12
		},
		{
			"dimension":4,
			"Row":9,
			"Col":9,
			"Value":5,
			"Candidates":33417,
			"Initial":true,
			"Sol":5
		},
		{
			"dimension":4,
			"Row":10,
			"Col":9,
			"Value":3,
			"Candidates":16897,
			"Initial":true,
			"Sol":3
		},
		{
			"dimension":4,
			"Row":11,
			"Col":9,
			"Value":2,
			"Candidates":49793,
			"Initial":true,
			"Sol":2
		},
		{
			"dimension":4,
			"Row":12,
			"Col":9,
			"Value":0,
			"Candidates":49160,
			"Initial":false,
			"Sol":15
		},
		{
			"dimension":4,
			"Row":13,
			"Col":9,
			"Value":0,
			"Candidates":841,
			"Initial":false,
			"Sol":7
		},
		{
			"dimension":4,
			"Row":14,
			"Col":9,
			"Value":0,
			"Candidates":385,
			"Initial":false,
			"Sol":1
		},
		{
			"dimension":4,
			"Row":15,
			"Col":9,
			"Value":0,
			"Candidates":841,
			"Initial":false,
			"Sol":10
		},
		{
			"dimension":4,
			"Row":16,
			"Col":9,
			"Value":11,
			"Candidates":969,
			"Initial":true,
			"Sol":11
		},
		{
			"dimension":4,
			"Row":1,
			"Col":10,
			"Value":9,
			"Candidates":18,
			"Initial":true,
			"Sol":9
		},
		{
			"dimension":4,
			"Row":2,
			"Col":10,
			"Value":0,
			"Candidates":16403,
			"Initial":false,
			"Sol":15
		},
		{
			"dimension":4,
			"Row":3,
			"Col":10,
			"Value":11,
			"Candidates":17,
			"Initial":true,
			"Sol":11
		},
		{
			"dimension":4,
			"Row":4,
			"Col":10,
			"Value":13,
			"Candidates":16402,
			"Initial":true,
			"Sol":13
		},
		{
			"dimension":4,
			"Row":5,
			"Col":10,
			"Value":8,
			"Candidates":40960,
			"Initial":true,
			"Sol":8
		},
		{
			"dimension":4,
			"Row":6,
			"Col":10,
			"Value":4,
			"Candidates":2,
			"Initial":true,
			"Sol":4
		},
		{
			"dimension":4,
			"Row":7,
			"Col":10,
			"Value":10,
			"Candidates":40977,
			"Initial":true,
			"Sol":10
		},
		{
			"dimension":4,
			"Row":8,
			"Col":10,
			"Value":0,
			"Candidates":8211,
			"Initial":false,
			"Sol":5
		},
		{
			"dimension":4,
			"Row":9,
			"Col":10,
			"Value":0,
			"Candidates":40961,
			"Initial":false,
			"Sol":1
		},
		{
			"dimension":4,
			"Row":10,
			"Col":10,
			"Value":12,
			"Candidates":24577,
			"Initial":true,
			"Sol":12
		},
		{
			"dimension":4,
			"Row":11,
			"Col":10,
			"Value":7,
			"Candidates":57345,
			"Initial":true,
			"Sol":7
		},
		{
			"dimension":4,
			"Row":12,
			"Col":10,
			"Value":0,
			"Candidates":57344,
			"Initial":false,
			"Sol":16
		},
		{
			"dimension":4,
			"Row":13,
			"Col":10,
			"Value":0,
			"Candidates":8199,
			"Initial":false,
			"Sol":2
		},
		{
			"dimension":4,
			"Row":14,
			"Col":10,
			"Value":6,
			"Candidates":21,
			"Initial":true,
			"Sol":6
		},
		{
			"dimension":4,
			"Row":15,
			"Col":10,
			"Value":0,
			"Candidates":8215,
			"Initial":false,
			"Sol":3
		},
		{
			"dimension":4,
			"Row":16,
			"Col":10,
			"Value":0,
			"Candidates":8209,
			"Initial":false,
			"Sol":14
		},
		{
			"dimension":4,
			"Row":1,
			"Col":11,
			"Value":0,
			"Candidates":90,
			"Initial":false,
			"Sol":7
		},
		{
			"dimension":4,
			"Row":2,
			"Col":11,
			"Value":0,
			"Candidates":19,
			"Initial":false,
			"Sol":5
		},
		{
			"dimension":4,
			"Row":3,
			"Col":11,
			"Value":16,
			"Candidates":217,
			"Initial":true,
			"Sol":16
		},
		{
			"dimension":4,
			"Row":4,
			"Col":11,
			"Value":3,
			"Candidates":154,
			"Initial":true,
			"Sol":3
		},
		{
			"dimension":4,
			"Row":5,
			"Col":11,
			"Value":0,
			"Candidates":8256,
			"Initial":false,
			"Sol":14
		},
		{
			"dimension":4,
			"Row":6,
			"Col":11,
			"Value":0,
			"Candidates":1282,
			"Initial":false,
			"Sol":2
		},
		{
			"dimension":4,
			"Row":7,
			"Col":11,
			"Value":0,
			"Candidates":8529,
			"Initial":false,
			"Sol":1
		},
		{
			"dimension":4,
			"Row":8,
			"Col":11,
			"Value":0,
			"Candidates":9299,
			"Initial":false,
			"Sol":11
		},
		{
			"dimension":4,
			"Row":9,
			"Col":11,
			"Value":0,
			"Candidates":8841,
			"Initial":false,
			"Sol":8
		},
		{
			"dimension":4,
			"Row":10,
			"Col":11,
			"Value":6,
			"Candidates":9729,
			"Initial":true,
			"Sol":6
		},
		{
			"dimension":4,
			"Row":11,
			"Col":11,
			"Value":0,
			"Candidates":8833,
			"Initial":false,
			"Sol":10
		},
		{
			"dimension":4,
			"Row":12,
			"Col":11,
			"Value":0,
			"Candidates":9224,
			"Initial":false,
			"Sol":4
		},
		{
			"dimension":4,
			"Row":13,
			"Col":11,
			"Value":15,
			"Candidates":11083,
			"Initial":true,
			"Sol":15
		},
		{
			"dimension":4,
			"Row":14,
			"Col":11,
			"Value":13,
			"Candidates":2449,
			"Initial":true,
			"Sol":13
		},
		{
			"dimension":4,
			"Row":15,
			"Col":11,
			"Value":0,
			"Candidates":9051,
			"Initial":false,
			"Sol":9
		},
		{
			"dimension":4,
			"Row":16,
			"Col":11,
			"Value":0,
			"Candidates":11225,
			"Initial":false,
			"Sol":12
		},
		{
			"dimension":4,
			"Row":1,
			"Col":12,
			"Value":0,
			"Candidates":90,
			"Initial":false,
			"Sol":2
		},
		{
			"dimension":4,
			"Row":2,
			"Col":12,
			"Value":10,
			"Candidates":19,
			"Initial":true,
			"Sol":10
		},
		{
			"dimension":4,
			"Row":3,
			"Col":12,
			"Value":0,
			"Candidates":217,
			"Initial":false,
			"Sol":1
		},
		{
			"dimension":4,
			"Row":4,
			"Col":12,
			"Value":12,
			"Candidates":154,
			"Initial":true,
			"Sol":12
		},
		{
			"dimension":4,
			"Row":5,
			"Col":12,
			"Value":6,
			"Candidates":8256,
			"Initial":true,
			"Sol":6
		},
		{
			"dimension":4,
			"Row":6,
			"Col":12,
			"Value":15,
			"Candidates":1026,
			"Initial":true,
			"Sol":15
		},
		{
			"dimension":4,
			"Row":7,
			"Col":12,
			"Value":3,
			"Candidates":8273,
			"Initial":true,
			"Sol":3
		},
		{
			"dimension":4,
			"Row":8,
			"Col":12,
			"Value":0,
			"Candidates":9299,
			"Initial":false,
			"Sol":7
		},
		{
			"dimension":4,
			"Row":9,
			"Col":12,
			"Value":0,
			"Candidates":8329,
			"Initial":false,
			"Sol":14
		},
		{
			"dimension":4,
			"Row":10,
			"Col":12,
			"Value":9,
			"Candidates":9217,
			"Initial":true,
			"Sol":9
		},
		{
			"dimension":4,
			"Row":11,
			"Col":12,
			"Value":13,
			"Candidates":8321,
			"Initial":true,
			"Sol":13
		},
		{
			"dimension":4,
			"Row":12,
			"Col":12,
			"Value":0,
			"Candidates":9224,
			"Initial":false,
			"Sol":11
		},
		{
			"dimension":4,
			"Row":13,
			"Col":12,
			"Value":0,
			"Candidates":8267,
			"Initial":false,
			"Sol":4
		},
		{
			"dimension":4,
			"Row":14,
			"Col":12,
			"Value":16,
			"Candidates":145,
			"Initial":true,
			"Sol":16
		},
		{
			"dimension":4,
			"Row":15,
			"Col":12,
			"Value":0,
			"Candidates":8283,
			"Initial":false,
			"Sol":5
		},
		{
			"dimension":4,
			"Row":16,
			"Col":12,
			"Value":0,
			"Candidates":8409,
			"Initial":false,
			"Sol":8
		},
		{
			"dimension":4,
			"Row":1,
			"Col":13,
			"Value":3,
			"Candidates":0,
			"Initial":true,
			"Sol":3
		},
		{
			"dimension":4,
			"Row":2,
			"Col":13,
			"Value":0,
			"Candidates":16640,
			"Initial":false,
			"Sol":9
		},
		{
			"dimension":4,
			"Row":3,
			"Col":13,
			"Value":10,
			"Candidates":8448,
			"Initial":true,
			"Sol":10
		},
		{
			"dimension":4,
			"Row":4,
			"Col":13,
			"Value":0,
			"Candidates":16640,
			"Initial":false,
			"Sol":15
		},
		{
			"dimension":4,
			"Row":5,
			"Col":13,
			"Value":11,
			"Candidates":26688,
			"Initial":true,
			"Sol":11
		},
		{
			"dimension":4,
			"Row":6,
			"Col":13,
			"Value":1,
			"Candidates":6530,
			"Initial":true,
			"Sol":1
		},
		{
			"dimension":4,
			"Row":7,
			"Col":13,
			"Value":0,
			"Candidates":31168,
			"Initial":false,
			"Sol":8
		},
		{
			"dimension":4,
			"Row":8,
			"Col":13,
			"Value":0,
			"Candidates":8258,
			"Initial":false,
			"Sol":2
		},
		{
			"dimension":4,
			"Row":9,
			"Col":13,
			"Value":0,
			"Candidates":14560,
			"Initial":false,
			"Sol":6
		},
		{
			"dimension":4,
			"Row":10,
			"Col":13,
			"Value":0,
			"Candidates":28736,
			"Initial":false,
			"Sol":13
		},
		{
			"dimension":4,
			"Row":11,
			"Col":13,
			"Value":0,
			"Candidates":26752,
			"Initial":false,
			"Sol":12
		},
		{
			"dimension":4,
			"Row":12,
			"Col":13,
			"Value":0,
			"Candidates":24640,
			"Initial":false,
			"Sol":14
		},
		{
			"dimension":4,
			"Row":13,
			"Col":13,
			"Value":5,
			"Candidates":8546,
			"Initial":true,
			"Sol":5
		},
		{
			"dimension":4,
			"Row":14,
			"Col":13,
			"Value":4,
			"Candidates":256,
			"Initial":true,
			"Sol":4
		},
		{
			"dimension":4,
			"Row":15,
			"Col":13,
			"Value":0,
			"Candidates":8546,
			"Initial":false,
			"Sol":7
		},
		{
			"dimension":4,
			"Row":16,
			"Col":13,
			"Value":16,
			"Candidates":8544,
			"Initial":true,
			"Sol":16
		},
		{
			"dimension":4,
			"Row":1,
			"Col":14,
			"Value":8,
			"Candidates":1048,
			"Initial":true,
			"Sol":8
		},
		{
			"dimension":4,
			"Row":2,
			"Col":14,
			"Value":0,
			"Candidates":50192,
			"Initial":false,
			"Sol":16
		},
		{
			"dimension":4,
			"Row":3,
			"Col":14,
			"Value":12,
			"Candidates":8216,
			"Initial":true,
			"Sol":12
		},
		{
			"dimension":4,
			"Row":4,
			"Col":14,
			"Value":0,
			"Candidates":49176,
			"Initial":false,
			"Sol":5
		},
		{
			"dimension":4,
			"Row":5,
			"Col":14,
			"Value":0,
			"Candidates":24640,
			"Initial":false,
			"Sol":7
		},
		{
			"dimension":4,
			"Row":6,
			"Col":14,
			"Value":6,
			"Candidates":4610,
			"Initial":true,
			"Sol":6
		},
		{
			"dimension":4,
			"Row":7,
			"Col":14,
			"Value":0,
			"Candidates":28736,
			"Initial":false,
			"Sol":13
		},
		{
			"dimension":4,
			"Row":8,
			"Col":14,
			"Value":0,
			"Candidates":8770,
			"Initial":false,
			"Sol":10
		},
		{
			"dimension":4,
			"Row":9,
			"Col":14,
			"Value":0,
			"Candidates":45640,
			"Initial":false,
			"Sol":4
		},
		{
			"dimension":4,
			"Row":10,
			"Col":14,
			"Value":0,
			"Candidates":29248,
			"Initial":false,
			"Sol":15
		},
		{
			"dimension":4,
			"Row":11,
			"Col":14,
			"Value":9,
			"Candidates":57872,
			"Initial":true,
			"Sol":9
		},
		{
			"dimension":4,
			"Row":12,
			"Col":14,
			"Value":1,
			"Candidates":57432,
			"Initial":true,
			"Sol":1
		},
		{
			"dimension":4,
			"Row":13,
			"Col":14,
			"Value":0,
			"Candidates":8770,
			"Initial":false,
			"Sol":14
		},
		{
			"dimension":4,
			"Row":14,
			"Col":14,
			"Value":0,
			"Candidates":1024,
			"Initial":false,
			"Sol":11
		},
		{
			"dimension":4,
			"Row":15,
			"Col":14,
			"Value":0,
			"Candidates":9794,
			"Initial":false,
			"Sol":2
		},
		{
			"dimension":4,
			"Row":16,
			"Col":14,
			"Value":3,
			"Candidates":8768,
			"Initial":true,
			"Sol":3
		},
		{
			"dimension":4,
			"Row":1,
			"Col":15,
			"Value":0,
			"Candidates":8,
			"Initial":false,
			"Sol":4
		},
		{
			"dimension":4,
			"Row":2,
			"Col":15,
			"Value":13,
			"Candidates":16640,
			"Initial":true,
			"Sol":13
		},
		{
			"dimension":4,
			"Row":3,
			"Col":15,
			"Value":0,
			"Candidates":8456,
			"Initial":false,
			"Sol":14
		},
		{
			"dimension":4,
			"Row":4,
			"Col":15,
			"Value":1,
			"Candidates":16648,
			"Initial":true,
			"Sol":1
		},
		{
			"dimension":4,
			"Row":5,
			"Col":15,
			"Value":5,
			"Candidates":24640,
			"Initial":true,
			"Sol":5
		},
		{
			"dimension":4,
			"Row":6,
			"Col":15,
			"Value":3,
			"Candidates":896,
			"Initial":true,
			"Sol":3
		},
		{
			"dimension":4,
			"Row":7,
			"Col":15,
			"Value":0,
			"Candidates":25024,
			"Initial":false,
			"Sol":15
		},
		{
			"dimension":4,
			"Row":8,
			"Col":15,
			"Value":16,
			"Candidates":8768,
			"Initial":true,
			"Sol":16
		},
		{
			"dimension":4,
			"Row":9,
			"Col":15,
			"Value":11,
			"Candidates":8936,
			"Initial":true,
			"Sol":11
		},
		{
			"dimension":4,
			"Row":10,
			"Col":15,
			"Value":2,
			"Candidates":25152,
			"Initial":true,
			"Sol":2
		},
		{
			"dimension":4,
			"Row":11,
			"Col":15,
			"Value":0,
			"Candidates":25216,
			"Initial":false,
			"Sol":8
		},
		{
			"dimension":4,
			"Row":12,
			"Col":15,
			"Value":0,
			"Candidates":24648,
			"Initial":false,
			"Sol":7
		},
		{
			"dimension":4,
			"Row":13,
			"Col":15,
			"Value":0,
			"Candidates":9056,
			"Initial":false,
			"Sol":6
		},
		{
			"dimension":4,
			"Row":14,
			"Col":15,
			"Value":0,
			"Candidates":256,
			"Initial":false,
			"Sol":9
		},
		{
			"dimension":4,
			"Row":15,
			"Col":15,
			"Value":12,
			"Candidates":9056,
			"Initial":true,
			"Sol":12
		},
		{
			"dimension":4,
			"Row":16,
			"Col":15,
			"Value":0,
			"Candidates":9056,
			"Initial":false,
			"Sol":10
		},
		{
			"dimension":4,
			"Row":1,
			"Col":16,
			"Value":0,
			"Candidates":1040,
			"Initial":false,
			"Sol":11
		},
		{
			"dimension":4,
			"Row":2,
			"Col":16,
			"Value":7,
			"Candidates":34064,
			"Initial":true,
			"Sol":7
		},
		{
			"dimension":4,
			"Row":3,
			"Col":16,
			"Value":2,
			"Candidates":8464,
			"Initial":true,
			"Sol":2
		},
		{
			"dimension":4,
			"Row":4,
			"Col":16,
			"Value":6,
			"Candidates":33040,
			"Initial":true,
			"Sol":6
		},
		{
			"dimension":4,
			"Row":5,
			"Col":16,
			"Value":4,
			"Candidates":10240,
			"Initial":true,
			"Sol":4
		},
		{
			"dimension":4,
			"Row":6,
			"Col":16,
			"Value":0,
			"Candidates":2816,
			"Initial":false,
			"Sol":12
		},
		{
			"dimension":4,
			"Row":7,
			"Col":16,
			"Value":0,
			"Candidates":10496,
			"Initial":false,
			"Sol":9
		},
		{
			"dimension":4,
			"Row":8,
			"Col":16,
			"Value":0,
			"Candidates":8704,
			"Initial":false,
			"Sol":14
		},
		{
			"dimension":4,
			"Row":9,
			"Col":16,
			"Value":0,
			"Candidates":43520,
			"Initial":false,
			"Sol":16
		},
		{
			"dimension":4,
			"Row":10,
			"Col":16,
			"Value":0,
			"Candidates":8704,
			"Initial":false,
			"Sol":10
		},
		{
			"dimension":4,
			"Row":11,
			"Col":16,
			"Value":3,
			"Candidates":43536,
			"Initial":true,
			"Sol":3
		},
		{
			"dimension":4,
			"Row":12,
			"Col":16,
			"Value":0,
			"Candidates":40976,
			"Initial":false,
			"Sol":5
		},
		{
			"dimension":4,
			"Row":13,
			"Col":16,
			"Value":0,
			"Candidates":8961,
			"Initial":false,
			"Sol":1
		},
		{
			"dimension":4,
			"Row":14,
			"Col":16,
			"Value":15,
			"Candidates":1281,
			"Initial":true,
			"Sol":15
		},
		{
			"dimension":4,
			"Row":15,
			"Col":16,
			"Value":8,
			"Candidates":9985,
			"Initial":true,
			"Sol":8
		},
		{
			"dimension":4,
			"Row":16,
			"Col":16,
			"Value":13,
			"Candidates":8961,
			"Initial":true,
			"Sol":13
		}
	],
	"difficulty":145,
	"dimension":4,
	"dimension2":16
}